{"apiVersion":"v1","kind":"Service","metadata":{"annotations":{"fabric8.io/iconUrl":"img/icons/funktion.png","prometheus.io/port":"9779","prometheus.io/scrape":"true"},"creationTimestamp":"2016-06-21T21:02:05Z","labels":{"group":"io.fabric8.funktion.quickstart","project":"funktion-nodejs-example","provider":"fabric8","version":"1.0-SNAPSHOT"},"name":"funktion-nodejs-example","namespace":"default","resourceVersion":"27106","selfLink":"/api/v1/namespaces/default/services/funktion-nodejs-example","uid":"68b459be-37f3-11e6-acbd-080027b5c2f4"},"spec":{"clusterIP":"172.30.212.232","deprecatedPublicIPs":[],"externalIPs":[],"portalIP":"172.30.212.232","ports":[{"nodePort":31672,"port":8080,"protocol":"TCP","targetPort":8080}],"selector":{"group":"io.fabric8.funktion.quickstart","project":"funktion-nodejs-example","provider":"fabric8"},"sessionAffinity":"None","type":"LoadBalancer"},"status":{"loadBalancer":{"ingress":[]}}}